{
    "$schema": "http://json-schema.org/draft-07/schema#",
    "type": "object",
    "properties": {
        "discountID": {
            "type": [
                "null",
                "string"
            ]
        },
        "name": {
            "type": [
                "null",
                "string"
            ]
        },
        "discountAmount": {
            "type": [
                "null",
                "string"
            ]
        },
        "discountPercent": {
            "type": [
                "null",
                "string"
            ]
        },
        "requireCustomer": {
            "type": [
                "null",
                "string"
            ]
        },
        "archived": {
            "type": [
                "null",
                "string"
            ]
        },
        "timeStamp": {
            "type": [
                "null",
                "string"
            ],
            "format": "date-time"
        }
    }
}